_stk.cpython-37m-x86_64-linux-gnu.so
libz.so
libz.so.1.2.11
libz.so.1
.libslibz/libgomp-3300acd3.so.1.0.0
.libs_stk/libgomp-3300acd3.so.1.0.0
python_stk-0.4.dist-info/top_level.txt
python_stk-0.4.dist-info/RECORD
python_stk-0.4.dist-info/METADATA
python_stk-0.4.dist-info/WHEEL
stk/__init__.py
