Metadata-Version: 2.1
Name: python-stk
Version: 0.4
Summary: UNKNOWN
Home-page: UNKNOWN
Author: Simon Ekström
Author-email: 
License: UNKNOWN
Platform: UNKNOWN
Requires-Dist: numpy
